.bzrignore
HISTORY.txt
README.txt
ez_setup.py
setup.cfg
setup.py
src/ClueReleaseManager.egg-info/PKG-INFO
src/ClueReleaseManager.egg-info/SOURCES.txt
src/ClueReleaseManager.egg-info/dependency_links.txt
src/ClueReleaseManager.egg-info/entry_points.txt
src/ClueReleaseManager.egg-info/not-zip-safe
src/ClueReleaseManager.egg-info/requires.txt
src/ClueReleaseManager.egg-info/top_level.txt
src/clue/__init__.py
src/clue/relmgr/__init__.py
src/clue/relmgr/cmdtool.py
src/clue/relmgr/main.py
src/clue/relmgr/model.py
src/clue/relmgr/pypi.py
src/clue/relmgr/tests.py
src/clue/relmgr/utils.py
src/clue/relmgr/wsgiapp.py
src/clue/relmgr/static/__init__.py
src/clue/relmgr/static/cluerelmgr.css
src/clue/relmgr/static/favicon.ico
src/clue/relmgr/templates/404.html
src/clue/relmgr/templates/__init__.py
src/clue/relmgr/templates/base.html
src/clue/relmgr/templates/browser.html
src/clue/relmgr/templates/distro.html
src/clue/relmgr/templates/listing.html
src/clue/relmgr/templates/pager.html
src/clue/relmgr/templates/search.html