Metadata-Version: 1.0
Name: ClueReleaseManager
Version: 0.3.3
Summary: An implementation of a PyPi server
Home-page: http://projects.serverzen.com/pm/p/cluemapper/ClueReleaseManager
Author: Rocky Burt
Author-email: rocky@serverzen.com
License: BSD
Platform: UNKNOWN
Classifier: Programming Language :: Python
Classifier: Topic :: Software Development :: Libraries :: Python Modules
